sena/__init__.py
sena-0.0.1.dist-info/METADATA
sena-0.0.1.dist-info/WHEEL
sena-0.0.1.dist-info/top_level.txt
sena-0.0.1.dist-info/RECORD
