Metadata-Version: 2.4
Name: sena
Version: 0.0.1
Summary: Dummy lock package for sena
Author: AutoPublisher
